Metadata-Version: 1.0
Name: bis-telegram-client-py
Version: 0.0.1
Summary: API BIS-сервиса \&quot;Telegram\&quot;
Home-page: UNKNOWN
Author: UNKNOWN
Author-email: UNKNOWN
License: UNKNOWN
Keywords: Swagger,API BIS-сервиса \&quot;Telegram\&quot;
Platform: UNKNOWN
